{
  "record_id": "hybrid-baseball--undated--baserunning-friction-game-ending-fixes-situational-stat-bugs",
  "source_path": "docs/aar-baserunning-friction-and-game-ending-fixes.md",
  "repo": "hybrid-baseball",
  "parsed_at": "2026-06-10",
  "genre_confidence": "high",
  "date": null,
  "title": "Baserunning Friction, Game-Ending Fixes, Situational Stat Bugs",
  "scope": null,
  "rationale": [],
  "delegation_events": [],
  "actions": [],
  "risk_posture": [],
  "validation_claims": [],
  "non_actions": [],
  "residual_risks": [],
  "open_hooks": [],
  "section_headers_original": [
    "After-Action Report \u2014 Baserunning Friction, Game-Ending Fixes, Situational Stat Bugs",
    "What the user asked for",
    "What landed",
    "1. Situational Stats \u2014 the 0% rendering bug",
    "2. Errors \u2014 DEFENSE_ERROR tuned above the rounding-noise floor",
    "3. Sim keeps resetting \u2014 SI cap",
    "4. Runner-out + 2C-failure realism pass",
    "5. Probabilistic baserunning advancement + TOA event + LOB",
    "6. Home/visitor gap \u2014 partial fix",
    "What was decided NOT to do",
    "Files changed",
    "Addendum \u2014 Home/visitor follow-up: items 1/2/3, edge cap, and the fixture-artifact reveal",
    "The diagnostic that mattered",
    "What stays from the home/visitor follow-up",
    "Where this points for the production app",
    "Production audit + the actual home-advantage source",
    "Open items (revised)",
    "Things to remember (updated)"
  ],
  "unmapped_content": null,
  "quality_vector": {
    "has_scope": false,
    "has_rationale": false,
    "has_delegation_record": false,
    "has_validation": false,
    "has_negative_space": false,
    "has_residual_risk": false
  },
  "parser_notes": "Structural skeleton only; full semantic extraction deferred."
}